{
  "version": 1,
  "generated_at": "2026-07-02T13:18:45.037268+00:00",
  "count": 115,
  "items": [
    {
      "kind": "other",
      "title": "World Cup Roundup: USA Moves On Despite Balogun's Red; Kane Rescues England",
      "title_ja": "ワールドカップ総括：Balogunの退場も USA が勝ち進む、Kane が England を救う",
      "excerpt": "Harry Kane and the USA highlighted Match Day 21 at the 2026 FIFA World Cup.",
      "excerpt_ja": "2026 FIFA ワールドカップ第21試合日は Harry Kane と USA が注目を集めた",
      "sources": [
        "FOX Sports NFL"
      ],
      "reliability": 0.5,
      "team_abbrev": null,
      "player_name": null,
      "coach_name": null,
      "published_at": "Wed, 01 Jul 2026 23:56:53 -0400",
      "url": "https://www.foxsports.com/stories/soccer/world-cup-roundup-usmnt-balogun-red-goal-harry-kane-rescues-england"
    },
    {
      "kind": "other",
      "title": "USMNT Player Ratings vs. Bosnia and Herzegovina: USA Rallies After Red Card",
      "title_ja": "USMNT 選手評価 vs Bosnia and Herzegovina：退場後に USA が巻き返し",
      "excerpt": "Maurice Edu rates the starting XI for the United States against Bosnia and Herzegovina at the FIFA World Cup.",
      "excerpt_ja": "Maurice Edu が FIFA ワールドカップでの Bosnia and Herzegovina 戦の USA スターティング11を採点",
      "sources": [
        "FOX Sports NFL"
      ],
      "reliability": 0.5,
      "team_abbrev": null,
      "player_name": null,
      "coach_name": null,
      "published_at": "Wed, 01 Jul 2026 23:49:28 -0400",
      "url": "https://www.foxsports.com/stories/soccer/usmnt-player-ratings-vs-bosnia-herzegovina-july-1"
    },
    {
      "kind": "other",
      "title": "2026 World Cup Odds: Which Nations are Favored to Reach Semifinals?",
      "title_ja": "2026 ワールドカップ オッズ：どの国が準決勝進出の有力候補か",
      "excerpt": "Which nations are most likely to make the final four? See the latest odds to reach the 2026 FIFA World Cup semifinals.",
      "excerpt_ja": "ベスト4 進出の可能性が最も高い国はどこか。2026 FIFA ワールドカップ準決勝進出の最新オッズをチェック",
      "sources": [
        "FOX Sports NFL"
      ],
      "reliability": 0.5,
      "team_abbrev": null,
      "player_name": null,
      "coach_name": null,
      "published_at": "Wed, 01 Jul 2026 22:56:52 -0400",
      "url": "https://www.foxsports.com/stories/soccer/2026-world-cup-odds-which-nations-favored-reach-semifinals"
    },
    {
      "kind": "other",
      "title": "How to Watch the 2026 FIFA World Cup: Scores, Schedule, Dates for Every Match",
      "title_ja": "2026 FIFA ワールドカップの視聴方法：全試合のスコア、スケジュール、日程",
      "excerpt": "We're tracking all the scores and results at the FIFA 2026 World Cup.",
      "excerpt_ja": "2026 FIFA ワールドカップの全スコアと結果を追跡中",
      "sources": [
        "FOX Sports NFL"
      ],
      "reliability": 0.5,
      "team_abbrev": null,
      "player_name": null,
      "coach_name": null,
      "published_at": "Wed, 01 Jul 2026 22:54:39 -0400",
      "url": "https://www.foxsports.com/stories/soccer/how-watch-2026-fifa-world-cup-full-schedule-dates-every-match"
    },
    {
      "kind": "other",
      "title": "2026 World Cup Odds: France, Argentina Favored For Finals Rematch",
      "title_ja": "2026 ワールドカップ オッズ：France と Argentina が決勝リマッチの有力候補",
      "excerpt": "France leads the oddsboard, but Argentina continues to rise. Check out the latest odds to reach the World Cup final after the group stage.",
      "excerpt_ja": "France がオッズボードのトップだが、Argentina は上昇を続けている。グループステージ後の決勝進出オッズの最新情報をチェック",
      "sources": [
        "FOX Sports NFL"
      ],
      "reliability": 0.5,
      "team_abbrev": null,
      "player_name": null,
      "coach_name": null,
      "published_at": "Wed, 01 Jul 2026 22:53:15 -0400",
      "url": "https://www.foxsports.com/stories/soccer/2026-world-cup-odds-spain-france-lead-race-reach-final"
    },
    {
      "kind": "other",
      "title": "Folarin Balogun Receives Red Card In Second Half Against Bosnia And Herzegovina",
      "title_ja": "Folarin Balogun、Bosnia and Herzegovina 戦の後半で退場処分",
      "excerpt": "Folarin Balogun received a controversial red card against Bosnia and Herzegovina.",
      "excerpt_ja": "Folarin Balogun は Bosnia and Herzegovina 戦で物議を醸す退場を受けた",
      "sources": [
        "FOX Sports NFL"
      ],
      "reliability": 0.5,
      "team_abbrev": null,
      "player_name": null,
      "coach_name": null,
      "published_at": "Wed, 01 Jul 2026 22:50:12 -0400",
      "url": "https://www.foxsports.com/stories/soccer/folarin-balogun-red-card-bosnia-and-herzegovina"
    },
    {
      "kind": "other",
      "title": "2026 World Cup Round Of 32: Who's Favored In First Knockout Stage Games?",
      "title_ja": "2026 ワールドカップ ラウンド・オブ・32：初のノックアウトステージで誰が有力か",
      "excerpt": "Check out the odds for the Round of 32, now that losses equal elimination at the 2026 World Cup.",
      "excerpt_ja": "2026 ワールドカップで敗北が脱落を意味するようになったラウンド・オブ・32のオッズをチェック",
      "sources": [
        "FOX Sports NFL"
      ],
      "reliability": 0.5,
      "team_abbrev": null,
      "player_name": null,
      "coach_name": null,
      "published_at": "Wed, 01 Jul 2026 22:48:02 -0400",
      "url": "https://www.foxsports.com/stories/soccer/2026-world-cup-round-32-odds"
    },
    {
      "kind": "other",
      "title": "2026 World Cup Odds: France Strengthens Grip As Favorites; USA Rises",
      "title_ja": "2026 ワールドカップ オッズ：France が優勝候補の座を強固に、USA は上昇",
      "excerpt": "Here are the latest odds to win the 2026 FIFA World Cup.",
      "excerpt_ja": "2026 FIFA ワールドカップ優勝の最新オッズはこちら",
      "sources": [
        "FOX Sports NFL"
      ],
      "reliability": 0.5,
      "team_abbrev": null,
      "player_name": null,
      "coach_name": null,
      "published_at": "Wed, 01 Jul 2026 22:44:57 -0400",
      "url": "https://www.foxsports.com/stories/soccer/world-cup-2026-champion-odds"
    },
    {
      "kind": "trade",
      "title": "2026-27 NBA Finals Odds: Spurs Favored; 76ers Rise After Landing Brown",
      "title_ja": "2026-27 NBA ファイナルズ オッズ：Spurs が有力、Brown 獲得後 76ers が上昇",
      "excerpt": "See the updated NBA title odds now that the Celtics have traded away one of their franchise cornerstones.",
      "excerpt_ja": "Celtics がフランチャイズの柱の一角をトレードに出した今、NBA チャンピオンシップの最新オッズをチェック",
      "sources": [
        "FOX Sports NFL"
      ],
      "reliability": 0.5,
      "team_abbrev": null,
      "player_name": null,
      "coach_name": null,
      "published_at": "Wed, 01 Jul 2026 22:36:26 -0400",
      "url": "https://www.foxsports.com/stories/nba/2026-27-nba-finals-odds"
    },
    {
      "kind": "rumor",
      "title": "Patriots scouting report: Reggie Gilliam is not a traditional thumper at fullback",
      "title_ja": "Patriots スカウティングレポート：Reggie Gilliam は従来型のタックリングブロッカーではない",
      "excerpt": "Previewing the Patriots fullback heading into his seventh NFL season.",
      "excerpt_ja": "Patriots フルバックが NFL 7年目のシーズンに向かう中、プレビューする",
      "sources": [
        "Yahoo Sports NFL"
      ],
      "reliability": 0.5,
      "team_abbrev": "NE",
      "player_name": null,
      "coach_name": null,
      "published_at": "Wed, 01 Jul 2026 21:53:13 +0000",
      "url": "https://sports.yahoo.com/articles/patriots-scouting-report-reggie-gilliam-215313415.html"
    },
    {
      "kind": "other",
      "title": "Where Jackson Powers-Johnson fits best on the Raiders’ offensive line",
      "title_ja": "Jackson Powers-Johnson が Raiders のオフェンスラインのどこに適合するか",
      "excerpt": "With Tyler Linderbaum manning the pivot, third-year lineman slated to focus on one of the guard spots under Rick Dennison",
      "excerpt_ja": "Tyler Linderbaum がセンターを務める中、3年目のOLは Rick Dennison の下でガード位置に焦点を当てる予定",
      "sources": [
        "Yahoo Sports NFL"
      ],
      "reliability": 0.5,
      "team_abbrev": "LV",
      "player_name": null,
      "coach_name": null,
      "published_at": "Wed, 01 Jul 2026 21:46:00 +0000",
      "url": "https://sports.yahoo.com/articles/where-jackson-powers-johnson-fits-214600573.html"
    },
    {
      "kind": "rumor",
      "title": "NBC could try to get both English and Spanish rights to 2030 World Cup",
      "title_ja": "NBC は 2030 ワールドカップの英語放映権とスペイン語放映権の両方を獲得しようとする可能性がある",
      "excerpt": "The World Cup rights for both the English- and Spanish-language broadcasts in the U.S. will be available in 2030 to the highest bidder.",
      "excerpt_ja": "2030 年の米国内でのワールドカップ放映権（英語およびスペイン語）は最高入札者に利用可能になる",
      "sources": [
        "Pro Football Talk"
      ],
      "reliability": 0.5,
      "team_abbrev": null,
      "player_name": null,
      "coach_name": null,
      "published_at": "Wed, 01 Jul 2026 21:38:07 -0400",
      "url": "https://www.nbcsports.com/nfl/profootballtalk/rumor-mill/news/nbc-could-try-to-get-both-english-and-spanish-rights-to-2030-world-cup"
    },
    {
      "kind": "other",
      "title": "Attorney: Blaise Taylor will appeal murder verdict",
      "title_ja": "弁護士：Blaise Taylor は殺人判決に控訴する予定",
      "excerpt": "On Wednesday, a jury convicted former Titans scout Blaise Taylor of murdering his pregnant girlfriend and her unborn child.",
      "excerpt_ja": "陪審団は水曜日、元 Titans スカウトの Blaise Taylor を妊娠中のガールフレンドと胎児を殺害した罪で有罪とした",
      "sources": [
        "Pro Football Talk"
      ],
      "reliability": 0.5,
      "team_abbrev": "TEN",
      "player_name": null,
      "coach_name": null,
      "published_at": "Wed, 01 Jul 2026 20:46:30 -0400",
      "url": "https://www.nbcsports.com/nfl/profootballtalk/rumor-mill/news/attorney-blaise-taylor-will-appeal-murder-verdict"
    },
    {
      "kind": "signing",
      "title": "Matt Miller's serious car accident has sparked scrutiny over his business dealings",
      "title_ja": "Matt Miller の重大交通事故は彼のビジネス取引に対する精査を引き起こした",
      "excerpt": "Last week's shocking news that ESPN draft analyst Matt Miller was involved in a serious car accident that resulted in the amputation of his left arm, along with other significant injuries, prompted an outpouring of support for him — both with words and, after his family created a GoFundMe effort, mo",
      "excerpt_ja": "先週の ESPN ドラフト解説者 Matt Miller が左腕の切断を含む重大な怪我を負った交通事故に関与したという衝撃的なニュースは、言葉による応援と家族が立ち上げた GoFundMe への支援をもたらした",
      "sources": [
        "Pro Football Talk"
      ],
      "reliability": 0.5,
      "team_abbrev": null,
      "player_name": null,
      "coach_name": null,
      "published_at": "Wed, 01 Jul 2026 20:32:29 -0400",
      "url": "https://www.nbcsports.com/nfl/profootballtalk/rumor-mill/news/matt-millers-serious-car-accident-has-sparked-scrutiny-over-his-business-dealings"
    },
    {
      "kind": "other",
      "title": "Chris Johnson brings back the Ice Bucket Challenge for ALS research",
      "title_ja": "Chris Johnson が ALS 研究のためアイスバケットチャレンジを復活させる",
      "excerpt": "Johnson is raising money to help find a cure for a horrible disease.",
      "excerpt_ja": "Johnson は恐ろしい病気の治療法を見つけるための資金調達に取り組んでいる",
      "sources": [
        "Pro Football Talk"
      ],
      "reliability": 0.5,
      "team_abbrev": null,
      "player_name": null,
      "coach_name": null,
      "published_at": "Wed, 01 Jul 2026 20:02:34 -0400",
      "url": "https://www.nbcsports.com/nfl/profootballtalk/rumor-mill/news/chris-johnson-brings-back-the-ice-bucket-challenge-for-als-research"
    },
    {
      "kind": "other",
      "title": "Malachi Lawrence working to come \"out of the shadows,\" into the spotlight",
      "title_ja": "Malachi Lawrence が『影の中から脱出』して注目を浴びることを目指す",
      "excerpt": "The Cowboys selected Ohio State safety Caleb Downs with the 11th overall pick.",
      "excerpt_ja": "Cowboys は Ohio State セーフティ Caleb Downs を全体11番目で指名",
      "sources": [
        "Pro Football Talk"
      ],
      "reliability": 0.5,
      "team_abbrev": "DAL",
      "player_name": null,
      "coach_name": null,
      "published_at": "Wed, 01 Jul 2026 18:28:46 -0400",
      "url": "https://www.nbcsports.com/nfl/profootballtalk/rumor-mill/news/malachi-lawrence-working-to-come-out-of-the-shadows-into-the-spotlight"
    },
    {
      "kind": "other",
      "title": "Lions officially waive Terrion Arnold",
      "title_ja": "Lions は公式に Terrion Arnold をウェーブ",
      "excerpt": "The claiming deadline is Monday, July 6.",
      "excerpt_ja": "クレーム期限は 7 月 6 日（月）",
      "sources": [
        "Pro Football Talk"
      ],
      "reliability": 0.5,
      "team_abbrev": "DET",
      "player_name": null,
      "coach_name": null,
      "published_at": "Wed, 01 Jul 2026 16:59:39 -0400",
      "url": "https://www.nbcsports.com/nfl/profootballtalk/rumor-mill/news/lions-officially-waive-terrion-arnold"
    },
    {
      "kind": "other",
      "title": "Jury convicts Blaise Taylor of murdering his pregnant girlfriend",
      "title_ja": "陪審団が Blaise Taylor に妊娠中のガールフレンド殺人罪で有罪評決",
      "excerpt": "Former Titans scout Blaise Taylor has been convicted of killing Jade Benning and her unborn child.",
      "excerpt_ja": "元 Titans スカウトの Blaise Taylor は Jade Benning と胎児を殺害した罪で有罪となった",
      "sources": [
        "Pro Football Talk"
      ],
      "reliability": 0.5,
      "team_abbrev": "TEN",
      "player_name": null,
      "coach_name": null,
      "published_at": "Wed, 01 Jul 2026 16:46:57 -0400",
      "url": "https://www.nbcsports.com/nfl/profootballtalk/rumor-mill/news/jury-convicts-blaise-taylor-of-murdering-his-pregnant-girlfriend"
    },
    {
      "kind": "presser",
      "title": "Report: Jonathan Jones is in \"advanced talks\" to leave CBS for The Athletic",
      "title_ja": "報道：Jonathan Jones は CBS から The Athletic への『最終段階の交渉』中",
      "excerpt": "In last week's lengthy article from the New York Times about Dianna Russini, the former NFL insider at The Athletic, a Times Company spokesperson said as to the possibility that The Athletic will hire a new NFL insider: “Not something I can confirm at that level of detail at this point.”",
      "excerpt_ja": "先週の New York Times の Dianna Russini（The Athletic 元 NFL インサイダー）に関する長編記事では、Times 社のスポークスマンが The Athletic の新 NFL インサイダー採用の可能性について『現段階では詳細についてお答えできません』とコメント",
      "sources": [
        "Pro Football Talk"
      ],
      "reliability": 0.5,
      "team_abbrev": null,
      "player_name": null,
      "coach_name": null,
      "published_at": "Wed, 01 Jul 2026 16:38:04 -0400",
      "url": "https://www.nbcsports.com/nfl/profootballtalk/rumor-mill/news/report-jonathan-jones-is-in-advanced-talks-to-leave-cbs-for-the-athletic"
    },
    {
      "kind": "other",
      "title": "Texans G Ed Ingram: We're doing a complete 180 on the offensive line",
      "title_ja": "Texans ガード Ed Ingram：オフェンスラインで完全に方針転換している",
      "excerpt": "There wasn't a lot to like about the Texans' offensive line play in 2025, but right guard Ed Ingram was able to do some good work for the team.",
      "excerpt_ja": "2025 年の Texans のオフェンスライン成績に褒める点は少なかったが、右ガード Ed Ingram はチームのために良い仕事をこなすことができた",
      "sources": [
        "Pro Football Talk"
      ],
      "reliability": 0.5,
      "team_abbrev": "HOU",
      "player_name": null,
      "coach_name": null,
      "published_at": "Wed, 01 Jul 2026 15:42:14 -0400",
      "url": "https://www.nbcsports.com/nfl/profootballtalk/rumor-mill/news/texans-g-ed-ingram-were-doing-a-complete-180-on-the-offensive-line"
    },
    {
      "kind": "injury",
      "title": "Javonte Williams on new contract: Hard work paid off, now I have more to prove",
      "title_ja": "Javonte Williams が新契約について語る：努力が報われた、これからさらに証明しなければならない",
      "excerpt": "After running back Javonte Williams went to Dallas on a one-year, $3.5 million contract last year, he gave the Cowboys more than their money's worth, having the best season of his career with 252 carries for 1,201 yards and 11 touchdowns.",
      "excerpt_ja": "ランニングバック Javonte Williams は昨年 Dallas と 1 年 350 万ドルの契約を交わしたが、252 キャリア、1201 ヤード、11 タッチダウンでキャリア最高シーズンを記録し、Cowboys から契約額以上の価値を引き出した",
      "sources": [
        "Pro Football Talk"
      ],
      "reliability": 0.5,
      "team_abbrev": "DAL",
      "player_name": null,
      "coach_name": null,
      "published_at": "Wed, 01 Jul 2026 14:37:39 -0400",
      "url": "https://www.nbcsports.com/nfl/profootballtalk/rumor-mill/news/javonte-williams-on-new-contract-hard-work-paid-off-now-i-have-more-to-prove"
    },
    {
      "kind": "other",
      "title": "Caleb Williams: We'll get the completion percentage up, make everyone feel warm and lovely",
      "title_ja": "Caleb Williams：コンプリーション率を上げて、みんなに温かくて良い気分を与える",
      "excerpt": "Bears quarterback Caleb Williams did well enough in the biggest moments to lead the team to a division title and a thrilling playoff win over the Packers last season, but there are still those who feel Williams doesn't do enough in the more routine moments.",
      "excerpt_ja": "Bears クォーターバック Caleb Williams は先シーズン、大事な場面で十分な活躍をしてディビジョンタイトルと Packers との劇的なプレーオフ勝利をもたらしたが、ルーチンプレーでもっと貢献すべきだという指摘もある",
      "sources": [
        "Pro Football Talk"
      ],
      "reliability": 0.5,
      "team_abbrev": "CHI",
      "player_name": null,
      "coach_name": null,
      "published_at": "Wed, 01 Jul 2026 13:27:27 -0400",
      "url": "https://www.nbcsports.com/nfl/profootballtalk/rumor-mill/news/caleb-williams-well-get-the-completion-percentage-up-make-everyone-feel-warm-and-lovely"
    },
    {
      "kind": "other",
      "title": "U.S. returns to World Cup action tonight at Levi's Stadium, with get-in price of $1,369",
      "title_ja": "USA は今夜 Levi's Stadium でワールドカップの試合に戻る、最安チケットは 1369 ドル",
      "excerpt": "The boys in red, white, and blue will be back in action tonight.",
      "excerpt_ja": "赤白青のユニフォームの選手たちが今夜復帰",
      "sources": [
        "Pro Football Talk"
      ],
      "reliability": 0.5,
      "team_abbrev": null,
      "player_name": null,
      "coach_name": null,
      "published_at": "Wed, 01 Jul 2026 12:47:03 -0400",
      "url": "https://www.nbcsports.com/nfl/profootballtalk/rumor-mill/news/u-s-returns-to-world-cup-action-tonight-at-levis-stadium-with-get-in-price-of-1-369"
    },
    {
      "kind": "rumor",
      "title": "ESPN retracts its latest Mike Pennel story, admits \"errors\" in the reporting",
      "title_ja": "ESPN が Mike Pennel 関連の最新ストーリーを撤回、報道の『誤り』を認める",
      "excerpt": "ESPN does an about-face regarding its reporting on a murder investigation in the Dominican Republic.",
      "excerpt_ja": "ESPN はドミニカ共和国での殺人事件捜査に関する報道で方針転換",
      "sources": [
        "Pro Football Talk"
      ],
      "reliability": 0.5,
      "team_abbrev": null,
      "player_name": null,
      "coach_name": null,
      "published_at": "Wed, 01 Jul 2026 10:59:10 -0400",
      "url": "https://www.nbcsports.com/nfl/profootballtalk/rumor-mill/news/espn-retracts-its-latest-mike-pennel-story-admits-errors-in-the-reporting"
    },
    {
      "kind": "other",
      "title": "New York Times says internal investigation of Dianna Russini \"is still ongoing\"",
      "title_ja": "New York Times は Dianna Russini に関する内部調査が『現在も進行中』と述べる",
      "excerpt": "Last night's article from the New York Times acknowledging that the bodycam footage from the Dianna Russini traffic stop didn't mesh with the publication's prior characterization of it included a nugget of related news buried near the bottom.",
      "excerpt_ja": "昨夜の New York Times の記事で Dianna Russini の交通取り締まり時のボディカメラ映像が同紙の以前の説明と矛盾していたことが認められ、その下部に関連する情報が掲載された",
      "sources": [
        "Pro Football Talk"
      ],
      "reliability": 0.5,
      "team_abbrev": null,
      "player_name": null,
      "coach_name": null,
      "published_at": "Wed, 01 Jul 2026 09:38:18 -0400",
      "url": "https://www.nbcsports.com/nfl/profootballtalk/rumor-mill/news/new-york-times-says-internal-investigation-of-dianna-russini-is-still-ongoing"
    },
    {
      "kind": "other",
      "title": "PFT has been with NBC for 17 years",
      "title_ja": "PFT は NBC と 17 年間の関係にある",
      "excerpt": "On July 1, 2009, we flipped the switch on our relationship with NBC.",
      "excerpt_ja": "2009 年 7 月 1 日、我々は NBC との関係をスタートさせた",
      "sources": [
        "Pro Football Talk"
      ],
      "reliability": 0.5,
      "team_abbrev": null,
      "player_name": null,
      "coach_name": null,
      "published_at": "Wed, 01 Jul 2026 09:13:56 -0400",
      "url": "https://www.nbcsports.com/nfl/profootballtalk/rumor-mill/news/pft-has-been-with-nbc-for-17-years"
    },
    {
      "kind": "signing",
      "title": "Eagles want Jalen Carter \"to be consistent with doing little things\"",
      "title_ja": "Eagles は Jalen Carter に『細かいプレーで一貫性を持つ』ことを求める",
      "excerpt": "Eagles defensive tackle Jalen Carter became eligible for a contract extension this offseason and the lack of one may have contributed to his limited participation in the team's practices this spring.",
      "excerpt_ja": "Eagles ディフェンシブタックル Jalen Carter はこのオフシーズンで契約延長資格を得たが、延長契約がないことが春のチーム練習への参加制限に寄与した可能性がある",
      "sources": [
        "Pro Football Talk"
      ],
      "reliability": 0.5,
      "team_abbrev": "PHI",
      "player_name": null,
      "coach_name": null,
      "published_at": "Wed, 01 Jul 2026 08:22:01 -0400",
      "url": "https://www.nbcsports.com/nfl/profootballtalk/rumor-mill/news/eagles-want-jalen-carter-to-be-consistent-with-doing-little-things"
    },
    {
      "kind": "other",
      "title": "DJ Moore buys out store's stock of his jerseys, leaves them for fans to have for free",
      "title_ja": "DJ Moore が店舗のジャージ在庫を全て買い取ってファンに無料で配布",
      "excerpt": "New Bills wide receiver DJ Moore hasn't wasted any time in endearing himself to fans in Buffalo.",
      "excerpt_ja": "Bills 新加入ワイドレシーバー DJ Moore はバッファロー地域のファンに好印象を与えるのに時間をかけなかった",
      "sources": [
        "Pro Football Talk"
      ],
      "reliability": 0.5,
      "team_abbrev": "BUF",
      "player_name": null,
      "coach_name": null,
      "published_at": "Wed, 01 Jul 2026 08:07:12 -0400",
      "url": "https://www.nbcsports.com/nfl/profootballtalk/rumor-mill/news/dj-moore-buys-out-stores-stock-of-his-jerseys-leaves-them-for-fans-to-have-for-free"
    },
    {
      "kind": "injury",
      "title": "Trey McBride on playing the Seahawks: \"Their defense is a bunch of s—t talkers\"",
      "title_ja": "Trey McBride が Seahawks 戦について語る：『彼らのディフェンスは口だけのグループだ』",
      "excerpt": "Cardinals tight end Trey McBride respects the Seahawks, but doesn't like them.",
      "excerpt_ja": "Cardinals タイトエンド Trey McBride は Seahawks を尊重しているが好きではない",
      "sources": [
        "Pro Football Talk"
      ],
      "reliability": 0.5,
      "team_abbrev": "ARI",
      "player_name": null,
      "coach_name": null,
      "published_at": "Wed, 01 Jul 2026 06:43:28 -0400",
      "url": "https://www.nbcsports.com/nfl/profootballtalk/rumor-mill/news/trey-mcbride-on-playing-the-seahawks-their-defense-is-a-bunch-of-s-t-talkers"
    },
    {
      "kind": "injury",
      "title": "Calais Campbell's brother charged with murder in the death of their mother",
      "title_ja": "Calais Campbell の兄が母親の死に関する殺人罪で起訴",
      "excerpt": "Ciarre Campbell, brother of Calais Campbell, was booked early Wednesday morning in Fulton County Jail on charges of murder, aggravated assault and possession of a firearm or knife.",
      "excerpt_ja": "Calais Campbell の兄 Ciarre Campbell は水曜日未明に Fulton County Jail に殺人罪、加重暴行罪、銃器または刃物所持罪で収監された",
      "sources": [
        "Pro Football Talk"
      ],
      "reliability": 0.5,
      "team_abbrev": null,
      "player_name": null,
      "coach_name": null,
      "published_at": "Wed, 01 Jul 2026 04:44:23 -0400",
      "url": "https://www.nbcsports.com/nfl/profootballtalk/rumor-mill/news/calais-campbells-brother-charged-with-murder-in-the-death-of-their-mother"
    },
    {
      "kind": "other",
      "title": "New York Times reiterates its view that Dianna Russini's handling of traffic stop was \"unacceptable conduct\"",
      "title_ja": "New York Times は Dianna Russini の交通取り締まり対応が『容認できない行為』だったという見解を改めて述べる",
      "excerpt": "The release of the bodycam footage from the Dianna Russini traffic stop put the New York Times in an awkward position.",
      "excerpt_ja": "Dianna Russini の交通取り締まりのボディカメラ映像の公開は New York Times を厳しい立場に置いた",
      "sources": [
        "Pro Football Talk"
      ],
      "reliability": 0.5,
      "team_abbrev": null,
      "player_name": null,
      "coach_name": null,
      "published_at": "Tue, 30 Jun 2026 23:03:39 -0400",
      "url": "https://www.nbcsports.com/nfl/profootballtalk/rumor-mill/news/new-york-times-reiterates-its-view-that-dianna-russinis-handling-of-traffic-stop-was-unacceptable-conduct"
    },
    {
      "kind": "other",
      "title": "DeMeco Ryans: C.J. Stroud, Nick Caley communicating much better this year",
      "title_ja": "DeMeco Ryans：C.J. Stroud と Nick Caley は今年のコミュニケーションがより良くなっている",
      "excerpt": "Quarterback C.J.",
      "excerpt_ja": "クォーターバック C.J.",
      "sources": [
        "Pro Football Talk"
      ],
      "reliability": 0.5,
      "team_abbrev": null,
      "player_name": null,
      "coach_name": null,
      "published_at": "Tue, 30 Jun 2026 17:42:12 -0400",
      "url": "https://www.nbcsports.com/nfl/profootballtalk/rumor-mill/news/demeco-ryans-c-j-stroud-nick-caley-communicating-much-better-this-year"
    },
    {
      "kind": "other",
      "title": "Titans will have eight open training camp practices",
      "title_ja": "Titans はトレーニングキャンプの公開練習を 8 試合実施",
      "excerpt": "The Titans will have eight open training camp practices this summer, the team announced Tuesday.",
      "excerpt_ja": "Titans は今夏、トレーニングキャンプの公開練習を 8 試合実施すると火曜日に発表",
      "sources": [
        "Pro Football Talk"
      ],
      "reliability": 0.5,
      "team_abbrev": "TEN",
      "player_name": null,
      "coach_name": null,
      "published_at": "Tue, 30 Jun 2026 17:33:08 -0400",
      "url": "https://www.nbcsports.com/nfl/profootballtalk/rumor-mill/news/titans-will-have-eight-open-training-camp-practices"
    },
    {
      "kind": "other",
      "title": "Chris Johnson's ALS fight has \"injected some hope\" in Tim Shaw's ALS fight",
      "title_ja": "Chris Johnson の ALS との戦いが Tim Shaw の ALS との戦いに『希望をもたらした』",
      "excerpt": "Former Titans linebacker Tim Shaw, who was diagnosed with ALS in 2014, was teammates with running back Chris Johnson for three seasons.",
      "excerpt_ja": "2014 年に ALS と診断された元 Titans ラインバッカー Tim Shaw は、ランニングバック Chris Johnson と 3 シーズン間チームメートだった",
      "sources": [
        "Pro Football Talk"
      ],
      "reliability": 0.5,
      "team_abbrev": "TEN",
      "player_name": null,
      "coach_name": null,
      "published_at": "Tue, 30 Jun 2026 17:24:11 -0400",
      "url": "https://www.nbcsports.com/nfl/profootballtalk/rumor-mill/news/chris-johnsons-als-fight-has-injected-some-hope-in-tim-shaws-als-fight"
    },
    {
      "kind": "signing",
      "title": "Brendan Sorsby and NFL agree he'll be eligible for 2027 draft",
      "title_ja": "Brendan Sorsby と NFL が 2027 ドラフト適格を認める合意に至る",
      "excerpt": "Sorsby, NFL, and NFLPA work out a settlement of his potential lawsuit against the league.",
      "excerpt_ja": "Sorsby、NFL、NFLPA がリーグに対する潜在的訴訟の合意に達する",
      "sources": [
        "Pro Football Talk"
      ],
      "reliability": 0.5,
      "team_abbrev": null,
      "player_name": null,
      "coach_name": null,
      "published_at": "Tue, 30 Jun 2026 17:10:36 -0400",
      "url": "https://www.nbcsports.com/nfl/profootballtalk/rumor-mill/news/brendan-sorsby-and-nfl-agree-hell-be-eligible-for-2027-draft"
    },
    {
      "kind": "other",
      "title": "Brendan Sorsby: I will focus on my recovery and preparing for the 2027 draft",
      "title_ja": "Brendan Sorsby：私は回復と 2027 ドラフトへの準備に焦点を当てる",
      "excerpt": "Sorsby wrote that the NFL's cancellation of the supplemental draft \"changes nothing about my recovery.\"",
      "excerpt_ja": "Sorsby は NFL の補足ドラフト中止が『自分の回復については何も変わらない』と述べた",
      "sources": [
        "Pro Football Talk"
      ],
      "reliability": 0.5,
      "team_abbrev": null,
      "player_name": null,
      "coach_name": null,
      "published_at": "Tue, 30 Jun 2026 17:08:18 -0400",
      "url": "https://www.nbcsports.com/nfl/profootballtalk/rumor-mill/news/brendan-sorsby-i-will-focus-on-my-recovery-and-preparing-for-the-2027-draft"
    },
    {
      "kind": "signing",
      "title": "Inside the Kyle Pitts deal",
      "title_ja": "Kyle Pitts 契約の内幕",
      "excerpt": "When Kyle Pitts was a rookie in 2021, Matt Ryan was his quarterback.",
      "excerpt_ja": "Kyle Pitts がルーキーだった 2021 年、Matt Ryan が彼のクォーターバックだった",
      "sources": [
        "Pro Football Talk"
      ],
      "reliability": 0.5,
      "team_abbrev": null,
      "player_name": null,
      "coach_name": null,
      "published_at": "Tue, 30 Jun 2026 16:59:22 -0400",
      "url": "https://www.nbcsports.com/nfl/profootballtalk/rumor-mill/news/inside-the-kyle-pitts-deal"
    },
    {
      "kind": "other",
      "title": "Nik Bonitto's goal is simple: Be a better player than the previous year",
      "title_ja": "Nik Bonitto の目標はシンプル：前年より優れたプレイヤーになること",
      "excerpt": "Broncos edge rusher Nik Bonitto was a finalist for Defensive Player of the Year, an award easily won by Myles Garrett.",
      "excerpt_ja": "Broncos エッジラッシャー Nik Bonitto は Defensive Player of the Year のファイナリストだったが、受賞は Myles Garrett に大差で決まった",
      "sources": [
        "Pro Football Talk"
      ],
      "reliability": 0.5,
      "team_abbrev": "DEN",
      "player_name": null,
      "coach_name": null,
      "published_at": "Tue, 30 Jun 2026 16:52:23 -0400",
      "url": "https://www.nbcsports.com/nfl/profootballtalk/rumor-mill/news/nik-bonittos-goal-is-simple-be-a-better-player-than-the-previous-year"
    },
    {
      "kind": "other",
      "title": "NFL offseason power rankings: No. 25 New York Giants quit messing around at head coach with John Harbaugh hire",
      "title_ja": "NFL オフシーズン パワーランキング：第 25 位 New York Giants、John Harbaugh 新任でヘッドコーチの試行錯誤をやめる",
      "excerpt": "The Giants have just two winning seasons since 2012.",
      "excerpt_ja": "Giants は 2012 年以来、勝ち越しシーズンがわずか 2 度",
      "sources": [
        "Yahoo Sports NFL"
      ],
      "reliability": 0.5,
      "team_abbrev": "NYG",
      "player_name": null,
      "coach_name": null,
      "published_at": "Thu, 02 Jul 2026 13:00:00 +0000",
      "url": "https://sports.yahoo.com/nfl/article/nfl-offseason-power-rankings-no-25-new-york-giants-quit-messing-around-at-head-coach-with-john-harbaugh-hire-130000989.html"
    },
    {
      "kind": "other",
      "title": "Jets 2026 Position Breakdown: Does New York have an adequate backup plan at quarterback in place?",
      "title_ja": "Jets 2026 ポジション分析：New York はクォーターバックのバックアップ態勢は十分か",
      "excerpt": "Breaking down the depth chart for every position group for the Jets. This time, we’ll go in depth at the quarterback position…",
      "excerpt_ja": "Jets の全ポジショングループのデプスチャートを詳細に分析。今回はクォーターバックポジションを掘り下げる",
      "sources": [
        "Yahoo Sports NFL"
      ],
      "reliability": 0.5,
      "team_abbrev": "NYJ",
      "player_name": null,
      "coach_name": null,
      "published_at": "Thu, 02 Jul 2026 12:56:44 +0000",
      "url": "https://sports.yahoo.com/articles/jets-2026-position-breakdown-does-125644976.html"
    },
    {
      "kind": "rumor",
      "title": "The Browns biggest “X-factor” on offense in 2026",
      "title_ja": null,
      "excerpt": "The Cleveland Browns roster on offense has a lot of hope, options but it is RB Quinshon Judkins that could change things",
      "excerpt_ja": null,
      "sources": [
        "Yahoo Sports NFL"
      ],
      "reliability": 0.5,
      "team_abbrev": "CLE",
      "player_name": null,
      "coach_name": null,
      "published_at": "Thu, 02 Jul 2026 12:52:27 +0000",
      "url": "https://sports.yahoo.com/articles/browns-biggest-x-factor-offense-125227834.html"
    },
    {
      "kind": "signing",
      "title": "Football fans: Vote for your favorite tailgate foods, get shot at $1000 prize",
      "title_ja": null,
      "excerpt": "Vote for your NFL team&#39;s signature dish in the Great American Tailgate bracket for a chance to win a $1,000 gift card.",
      "excerpt_ja": null,
      "sources": [
        "Yahoo Sports NFL"
      ],
      "reliability": 0.5,
      "team_abbrev": null,
      "player_name": null,
      "coach_name": null,
      "published_at": "Thu, 02 Jul 2026 12:51:14 +0000",
      "url": "https://sports.yahoo.com/articles/football-fans-vote-favorite-tailgate-125114205.html"
    },
    {
      "kind": "rumor",
      "title": "Buffalo Bills 2026 scouting report: WR Stephen Gosnell",
      "title_ja": null,
      "excerpt": "Can this second-year player break camp with the 53-man roster this year?",
      "excerpt_ja": null,
      "sources": [
        "Yahoo Sports NFL"
      ],
      "reliability": 0.5,
      "team_abbrev": "BUF",
      "player_name": null,
      "coach_name": null,
      "published_at": "Thu, 02 Jul 2026 12:01:11 +0000",
      "url": "https://sports.yahoo.com/articles/buffalo-bills-2026-scouting-report-120111070.html"
    },
    {
      "kind": "rumor",
      "title": "3 Panthers have been named to the NFL Top 100; will that be all?",
      "title_ja": null,
      "excerpt": "Which Panthers players could we see next on the NFLs Top 100 Players of 2026?",
      "excerpt_ja": null,
      "sources": [
        "Yahoo Sports NFL"
      ],
      "reliability": 0.5,
      "team_abbrev": "CAR",
      "player_name": null,
      "coach_name": null,
      "published_at": "Thu, 02 Jul 2026 12:00:00 +0000",
      "url": "https://sports.yahoo.com/articles/3-panthers-named-nfl-top-120000904.html"
    },
    {
      "kind": "other",
      "title": "Pathway to a winning season for 2026 Miami Dolphins",
      "title_ja": null,
      "excerpt": "Most experts predict a rough season for Miami in 2026. What if those experts are wrong?",
      "excerpt_ja": null,
      "sources": [
        "Yahoo Sports NFL"
      ],
      "reliability": 0.5,
      "team_abbrev": "MIA",
      "player_name": null,
      "coach_name": null,
      "published_at": "Thu, 02 Jul 2026 12:00:00 +0000",
      "url": "https://sports.yahoo.com/articles/pathway-winning-season-2026-miami-120000608.html"
    },
    {
      "kind": "other",
      "title": "Mailbag: Do the Detroit Lions HAVE to add a CB to replace Terrion Arnold?",
      "title_ja": null,
      "excerpt": "﻿We discuss how desperate the Detroit Lions are at cornerback after Terrion Arnold’s release.",
      "excerpt_ja": null,
      "sources": [
        "Yahoo Sports NFL"
      ],
      "reliability": 0.5,
      "team_abbrev": "DET",
      "player_name": null,
      "coach_name": null,
      "published_at": "Thu, 02 Jul 2026 12:00:00 +0000",
      "url": "https://sports.yahoo.com/articles/mailbag-detroit-lions-add-cb-120000768.html"
    },
    {
      "kind": "rumor",
      "title": "Fleur-de-links, July 2: Could this wide receiver quietly be a game changer",
      "title_ja": null,
      "excerpt": "Here are today&#39;s Saints news links",
      "excerpt_ja": null,
      "sources": [
        "Yahoo Sports NFL"
      ],
      "reliability": 0.5,
      "team_abbrev": "NO",
      "player_name": null,
      "coach_name": null,
      "published_at": "Thu, 02 Jul 2026 11:45:00 +0000",
      "url": "https://sports.yahoo.com/articles/fleur-links-july-2-could-114500717.html"
    },
    {
      "kind": "signing",
      "title": "Stealing one player from every division rival for the Titans",
      "title_ja": null,
      "excerpt": "An exercise designed to pluck one player from every division rival for the Tennessee Titans.",
      "excerpt_ja": null,
      "sources": [
        "Yahoo Sports NFL"
      ],
      "reliability": 0.5,
      "team_abbrev": "TEN",
      "player_name": null,
      "coach_name": null,
      "published_at": "Thu, 02 Jul 2026 11:30:00 +0000",
      "url": "https://sports.yahoo.com/articles/stealing-one-player-every-division-113000232.html"
    },
    {
      "kind": "other",
      "title": "6-foot-9, 268-pound Aussie Ben Te Kura quits rugby to pursue NFL career",
      "title_ja": null,
      "excerpt": "The tallest player in the history of Australia&#39;s National Rugby League is walking away to pursue an NFL career.",
      "excerpt_ja": null,
      "sources": [
        "Yahoo Sports NFL"
      ],
      "reliability": 0.54,
      "team_abbrev": null,
      "player_name": null,
      "coach_name": null,
      "published_at": "Thu, 02 Jul 2026 11:19:32 +0000",
      "url": "https://sports.yahoo.com/articles/6-foot-9-268-pound-111932604.html"
    },
    {
      "kind": "other",
      "title": "Cowboys news: Breaking down who needs to step up in 2026",
      "title_ja": null,
      "excerpt": "Check out the latest Dallas Cowboys news!",
      "excerpt_ja": null,
      "sources": [
        "Yahoo Sports NFL"
      ],
      "reliability": 0.5,
      "team_abbrev": "DAL",
      "player_name": null,
      "coach_name": null,
      "published_at": "Thu, 02 Jul 2026 11:00:00 +0000",
      "url": "https://sports.yahoo.com/articles/cowboys-news-breaking-down-needs-110000816.html"
    },
    {
      "kind": "other",
      "title": "The Cardinals’ rookie who should be getting more attention",
      "title_ja": null,
      "excerpt": "﻿Lots of changes from last year’s roster",
      "excerpt_ja": null,
      "sources": [
        "Yahoo Sports NFL"
      ],
      "reliability": 0.5,
      "team_abbrev": "ARI",
      "player_name": null,
      "coach_name": null,
      "published_at": "Thu, 02 Jul 2026 11:00:00 +0000",
      "url": "https://sports.yahoo.com/articles/cardinals-rookie-getting-more-attention-110000779.html"
    },
    {
      "kind": "other",
      "title": "2026 Season Opener Countdown: 73 Days Remaining",
      "title_ja": null,
      "excerpt": "We continue our countdown to the Panthers opening the 2026 season against the Chicago Bears",
      "excerpt_ja": null,
      "sources": [
        "Yahoo Sports NFL"
      ],
      "reliability": 0.5,
      "team_abbrev": "CAR",
      "player_name": null,
      "coach_name": null,
      "published_at": "Thu, 02 Jul 2026 11:00:00 +0000",
      "url": "https://sports.yahoo.com/articles/2026-season-opener-countdown-73-110000339.html"
    },
    {
      "kind": "other",
      "title": "New York Jets News: Karl Dunbar Leads Revamped Defensive Line",
      "title_ja": null,
      "excerpt": "Your daily links to the New York Jets",
      "excerpt_ja": null,
      "sources": [
        "Yahoo Sports NFL"
      ],
      "reliability": 0.5,
      "team_abbrev": "NYJ",
      "player_name": null,
      "coach_name": null,
      "published_at": "Thu, 02 Jul 2026 11:00:00 +0000",
      "url": "https://sports.yahoo.com/articles/york-jets-news-karl-dunbar-110000293.html"
    },
    {
      "kind": "other",
      "title": "4 Bengals selected in NFL.com’s 7-round mock draft of active players",
      "title_ja": null,
      "excerpt": "The idea is to win now.",
      "excerpt_ja": null,
      "sources": [
        "Yahoo Sports NFL"
      ],
      "reliability": 0.5,
      "team_abbrev": "CIN",
      "player_name": null,
      "coach_name": null,
      "published_at": "Thu, 02 Jul 2026 10:30:00 +0000",
      "url": "https://sports.yahoo.com/articles/4-bengals-selected-nfl-com-103000041.html"
    },
    {
      "kind": "other",
      "title": "Chiefs News 7/2: Kansas City predicted to miss 2026 playoffs",
      "title_ja": null,
      "excerpt": "The latest Chiefs news, brought fresh to you every morning!",
      "excerpt_ja": null,
      "sources": [
        "Yahoo Sports NFL"
      ],
      "reliability": 0.5,
      "team_abbrev": "KC",
      "player_name": null,
      "coach_name": null,
      "published_at": "Thu, 02 Jul 2026 10:30:00 +0000",
      "url": "https://sports.yahoo.com/articles/chiefs-news-7-2-kansas-103000882.html"
    },
    {
      "kind": "other",
      "title": "Cleveland Browns news (7/2): Hot town, summer in the city",
      "title_ja": null,
      "excerpt": "﻿﻿﻿﻿﻿﻿﻿﻿﻿﻿﻿﻿﻿﻿﻿﻿﻿﻿﻿﻿﻿﻿﻿﻿﻿﻿﻿﻿﻿﻿﻿﻿﻿﻿﻿﻿﻿﻿﻿﻿﻿The latest Cleveland Browns news and notes from around the NFL in today’s edition of the Daily Dawg Chow.﻿",
      "excerpt_ja": null,
      "sources": [
        "Yahoo Sports NFL"
      ],
      "reliability": 0.5,
      "team_abbrev": "CLE",
      "player_name": null,
      "coach_name": null,
      "published_at": "Thu, 02 Jul 2026 10:30:00 +0000",
      "url": "https://sports.yahoo.com/articles/cleveland-browns-news-7-2-103000496.html"
    },
    {
      "kind": "other",
      "title": "Giants news, 7/2: Eli on Year 2 jump for Jaxson Dart, stacking up the tight end room",
      "title_ja": null,
      "excerpt": "New York Giants headlines for Thursday, July 2nd",
      "excerpt_ja": null,
      "sources": [
        "Yahoo Sports NFL"
      ],
      "reliability": 0.5,
      "team_abbrev": "NYG",
      "player_name": null,
      "coach_name": null,
      "published_at": "Thu, 02 Jul 2026 10:00:00 +0000",
      "url": "https://sports.yahoo.com/articles/giants-news-7-2-eli-100000495.html"
    },
    {
      "kind": "other",
      "title": "Jaylen Waddle and Courtland Sutton rank sixth in CBS Sports’ dynamic duo wide receiver ranking",
      "title_ja": null,
      "excerpt": "Will 2026 be the year that the Denver Broncos once against boast two 1,000-yard wide receivers?",
      "excerpt_ja": null,
      "sources": [
        "Yahoo Sports NFL"
      ],
      "reliability": 0.5,
      "team_abbrev": "DEN",
      "player_name": null,
      "coach_name": null,
      "published_at": "Thu, 02 Jul 2026 10:00:00 +0000",
      "url": "https://sports.yahoo.com/articles/jaylen-waddle-courtland-sutton-rank-100000910.html"
    },
    {
      "kind": "other",
      "title": "4 NFL teams having the most puzzling offseasons: What are Colts, Jaguars doing?",
      "title_ja": null,
      "excerpt": "Every offseason teams across the NFL make head-scratching decisions. Here are some of the most puzzling from this year.",
      "excerpt_ja": null,
      "sources": [
        "Yahoo Sports NFL"
      ],
      "reliability": 0.5,
      "team_abbrev": "IND",
      "player_name": null,
      "coach_name": null,
      "published_at": "Thu, 02 Jul 2026 09:22:21 +0000",
      "url": "https://sports.yahoo.com/articles/4-nfl-teams-having-most-092221554.html"
    },
    {
      "kind": "other",
      "title": "Portugal vs. Croatia Prediction, Odds, Picks For World Cup Match",
      "title_ja": null,
      "excerpt": "Check out the odds for the Portugal vs. Croatia Round of 32 matchup at the 2026 FIFA World Cup.",
      "excerpt_ja": null,
      "sources": [
        "FOX Sports NFL"
      ],
      "reliability": 0.5,
      "team_abbrev": null,
      "player_name": null,
      "coach_name": null,
      "published_at": "Thu, 02 Jul 2026 09:00:40 -0400",
      "url": "https://www.foxsports.com/stories/soccer/portugal-vs-croatia-prediction-odds-picks-world-cup-match"
    },
    {
      "kind": "other",
      "title": "49ers News: Levi’s has been blessed",
      "title_ja": null,
      "excerpt": "Your daily San Francisco 49ers news for Thursday, July 2nd, 2026",
      "excerpt_ja": null,
      "sources": [
        "Yahoo Sports NFL"
      ],
      "reliability": 0.5,
      "team_abbrev": "SF",
      "player_name": null,
      "coach_name": null,
      "published_at": "Thu, 02 Jul 2026 09:00:00 +0000",
      "url": "https://sports.yahoo.com/articles/49ers-news-levi-blessed-090000383.html"
    },
    {
      "kind": "other",
      "title": "Can Dan Quinn extend his win streak against the Giants to 5-0? - 5 O’Clock Club",
      "title_ja": null,
      "excerpt": "Hogs Haven looks at coaching & roster changes that affect this key Week 5 NFC East game between the Giants & Commanders",
      "excerpt_ja": null,
      "sources": [
        "Yahoo Sports NFL"
      ],
      "reliability": 0.5,
      "team_abbrev": "NYG",
      "player_name": null,
      "coach_name": null,
      "published_at": "Thu, 02 Jul 2026 09:00:00 +0000",
      "url": "https://sports.yahoo.com/articles/dan-quinn-extend-win-streak-090000527.html"
    },
    {
      "kind": "signing",
      "title": "NFL Network-Comcast standoff enters its third month",
      "title_ja": null,
      "excerpt": "Xfinity cable viewers still can&#39;t watch NFL Network, and won&#39;t have NFL RedZone if a deal isn&#39;t reached by Week One.",
      "excerpt_ja": null,
      "sources": [
        "Yahoo Sports NFL"
      ],
      "reliability": 0.54,
      "team_abbrev": null,
      "player_name": null,
      "coach_name": null,
      "published_at": "Thu, 02 Jul 2026 08:51:44 +0000",
      "url": "https://sports.yahoo.com/articles/nfl-network-comcast-standoff-enters-085144543.html"
    },
    {
      "kind": "other",
      "title": "How to Watch Switzerland vs. Algeria: TV Channel, Live Stream, Time",
      "title_ja": null,
      "excerpt": "Learn which TV channel or how to live stream the Switzerland and Algeria FIFA World Cup match.",
      "excerpt_ja": null,
      "sources": [
        "FOX Sports NFL"
      ],
      "reliability": 0.5,
      "team_abbrev": null,
      "player_name": null,
      "coach_name": null,
      "published_at": "Thu, 02 Jul 2026 08:45:04 -0400",
      "url": "https://www.foxsports.com/stories/soccer/switzerland-vs-algeria-how-to-watch-tv-channel-live-stream-2026-fifa-world-cup-round-of-32"
    },
    {
      "kind": "injury",
      "title": "Texans waive DB Ajani Carter, LB Xavier Thomas off of IR",
      "title_ja": null,
      "excerpt": "The Texans made a pair of moves involving players on their injured reserve list on Wednesday.",
      "excerpt_ja": null,
      "sources": [
        "Pro Football Talk"
      ],
      "reliability": 0.5,
      "team_abbrev": "HOU",
      "player_name": null,
      "coach_name": null,
      "published_at": "Thu, 02 Jul 2026 08:23:52 -0400",
      "url": "https://www.nbcsports.com/nfl/profootballtalk/rumor-mill/news/texans-waive-db-ajani-carter-lb-xavier-thomas-off-of-ir"
    },
    {
      "kind": "other",
      "title": "How to Watch the World Cup Today: Schedule, Times, TV, Streaming for Spain, Portugal, More",
      "title_ja": null,
      "excerpt": "Spain, Portugal and Switzerland headline the World Cup Round of 32 today. Full schedule, kickoff times and how to watch on FOX.",
      "excerpt_ja": null,
      "sources": [
        "FOX Sports NFL"
      ],
      "reliability": 0.5,
      "team_abbrev": null,
      "player_name": null,
      "coach_name": null,
      "published_at": "Thu, 02 Jul 2026 08:05:19 -0400",
      "url": "https://www.foxsports.com/stories/soccer/how-watch-world-cup-today-schedule-times-tv-streaming-spain-portugal-more"
    },
    {
      "kind": "other",
      "title": "How to Watch Spain vs. Austria: TV Channel, Live Stream, Time",
      "title_ja": null,
      "excerpt": "Learn which TV channel or how to live stream the Spain and Austria FIFA World Cup match.",
      "excerpt_ja": null,
      "sources": [
        "FOX Sports NFL"
      ],
      "reliability": 0.5,
      "team_abbrev": null,
      "player_name": null,
      "coach_name": null,
      "published_at": "Thu, 02 Jul 2026 07:39:26 -0400",
      "url": "https://www.foxsports.com/stories/soccer/spain-vs-austria-how-to-watch-tv-channel-live-stream-2026-fifa-world-cup-round-of-32"
    },
    {
      "kind": "other",
      "title": "6-foot-9, 268-pound Aussie Ben Te Kura quits rugby to pursue NFL career",
      "title_ja": null,
      "excerpt": "The tallest player in the history of Australia's National Rugby League is walking away to pursue an NFL career.",
      "excerpt_ja": null,
      "sources": [
        "Pro Football Talk"
      ],
      "reliability": 0.54,
      "team_abbrev": null,
      "player_name": null,
      "coach_name": null,
      "published_at": "Thu, 02 Jul 2026 07:19:32 -0400",
      "url": "https://www.nbcsports.com/nfl/profootballtalk/rumor-mill/news/6-foot-9-268-pound-aussie-ben-te-kura-quits-rugby-to-pursue-nfl-career"
    },
    {
      "kind": "other",
      "title": "bet365 Bonus Code: Bet $10, Get $150 in Bonus Bets Win or Lose with Promo Code FOX365",
      "title_ja": null,
      "excerpt": "Claim the bet365 Sportsbook promo code which give you $365 in bonus bets.",
      "excerpt_ja": null,
      "sources": [
        "FOX Sports NFL"
      ],
      "reliability": 0.5,
      "team_abbrev": null,
      "player_name": null,
      "coach_name": null,
      "published_at": "Thu, 02 Jul 2026 07:00:39 -0400",
      "url": "https://www.foxsports.com/stories/betting/bet365-promo-code"
    },
    {
      "kind": "injury",
      "title": "Algeria Coach Going Against Former Team Switzerland In World Cup Knockout Round",
      "title_ja": null,
      "excerpt": "Swiss forward Breel Embolo credits Algeria coach Vladimir Petkovic with raising Switzerland’s national team during his seven years at the helm, and now he'll face him in the World Cup.",
      "excerpt_ja": null,
      "sources": [
        "FOX Sports NFL"
      ],
      "reliability": 0.5,
      "team_abbrev": null,
      "player_name": null,
      "coach_name": null,
      "published_at": "Thu, 02 Jul 2026 07:00:28 -0400",
      "url": "https://www.foxsports.com/stories/soccer/2026-fifa-world-cup-algeria-switzerland-vladimir-petkovic"
    },
    {
      "kind": "other",
      "title": "Eagles 2026 most important list: Cam Jurgens",
      "title_ja": null,
      "excerpt": "Center Cam Jurgens takes his place on the list of the most important Eagles of 2026.",
      "excerpt_ja": null,
      "sources": [
        "Yahoo Sports NFL"
      ],
      "reliability": 0.5,
      "team_abbrev": "PHI",
      "player_name": null,
      "coach_name": null,
      "published_at": "Thu, 02 Jul 2026 07:00:00 +0000",
      "url": "https://sports.yahoo.com/articles/eagles-2026-most-important-list-070000733.html"
    },
    {
      "kind": "injury",
      "title": "2026-2027 College Basketball Offseason Buzz: St. John's Transfer Out For Season",
      "title_ja": null,
      "excerpt": "We're tracking notable injuries, news and happenings across men's and women's college basketball during the 2026-2027 offeason.",
      "excerpt_ja": null,
      "sources": [
        "FOX Sports NFL"
      ],
      "reliability": 0.5,
      "team_abbrev": null,
      "player_name": null,
      "coach_name": null,
      "published_at": "Thu, 02 Jul 2026 06:41:29 -0400",
      "url": "https://www.foxsports.com/stories/college-basketball/college-basketball-2026-2027-buzz-news-injuries-transfers"
    },
    {
      "kind": "other",
      "title": "Spain vs. Austria Prediction, Odds, Picks For World Cup Match",
      "title_ja": null,
      "excerpt": "Check out the odds for the Spain vs. Austria Round of 32 matchup at the 2026 FIFA World Cup.",
      "excerpt_ja": null,
      "sources": [
        "FOX Sports NFL"
      ],
      "reliability": 0.5,
      "team_abbrev": null,
      "player_name": null,
      "coach_name": null,
      "published_at": "Thu, 02 Jul 2026 05:00:56 -0400",
      "url": "https://www.foxsports.com/stories/soccer/spain-vs-austria-prediction-odds-picks-world-cup-match"
    },
    {
      "kind": "signing",
      "title": "NFL Network-Comcast standoff enters its third month",
      "title_ja": null,
      "excerpt": "Xfinity cable viewers still can't watch NFL Network, and won't have NFL RedZone if a deal isn't reached by Week One.",
      "excerpt_ja": null,
      "sources": [
        "Pro Football Talk"
      ],
      "reliability": 0.54,
      "team_abbrev": null,
      "player_name": null,
      "coach_name": null,
      "published_at": "Thu, 02 Jul 2026 04:51:44 -0400",
      "url": "https://www.nbcsports.com/nfl/profootballtalk/rumor-mill/news/nfl-network-comcast-standoff-enters-its-third-month"
    },
    {
      "kind": "other",
      "title": "Resilience, Belief And 'Steely Focus': How USA Weathered Storm For Gritty World Cup Win",
      "title_ja": null,
      "excerpt": "The USA showed its character in a gritty round of 32 win over Bosnia and Herzegovina.",
      "excerpt_ja": null,
      "sources": [
        "FOX Sports NFL"
      ],
      "reliability": 0.5,
      "team_abbrev": null,
      "player_name": null,
      "coach_name": null,
      "published_at": "Thu, 02 Jul 2026 04:09:15 -0400",
      "url": "https://www.foxsports.com/stories/soccer/resilience-belief-steely-focus-how-usa-weathered-storm-gritty-world-cup-win"
    },
    {
      "kind": "other",
      "title": "ESPN hates the Rams’ offseason",
      "title_ja": null,
      "excerpt": "Sean McVay’s bullet board material for Rams players starts with a “C+”",
      "excerpt_ja": null,
      "sources": [
        "Yahoo Sports NFL"
      ],
      "reliability": 0.5,
      "team_abbrev": "LAR",
      "player_name": null,
      "coach_name": null,
      "published_at": "Thu, 02 Jul 2026 02:28:36 +0000",
      "url": "https://sports.yahoo.com/articles/espn-hates-rams-offseason-022836459.html"
    },
    {
      "kind": "other",
      "title": "Can The USA Appeal Folarin Balogun's World Cup Red Card?",
      "title_ja": null,
      "excerpt": "Can the USA appeal the red card given to Folarin Balogun? Our World Cup rules expert explains.",
      "excerpt_ja": null,
      "sources": [
        "FOX Sports NFL"
      ],
      "reliability": 0.5,
      "team_abbrev": null,
      "player_name": null,
      "coach_name": null,
      "published_at": "Thu, 02 Jul 2026 01:19:07 -0400",
      "url": "https://www.foxsports.com/stories/soccer/world-cup-red-card-balogun-can-usa-appeal"
    },
    {
      "kind": "rumor",
      "title": "How Rams could fall apart by the time Ty Simpson takes over",
      "title_ja": null,
      "excerpt": "Why this “all in” approach feels different than last time and how it could lead to a different result",
      "excerpt_ja": null,
      "sources": [
        "Yahoo Sports NFL"
      ],
      "reliability": 0.5,
      "team_abbrev": "LAR",
      "player_name": null,
      "coach_name": null,
      "published_at": "Thu, 02 Jul 2026 01:15:00 +0000",
      "url": "https://sports.yahoo.com/articles/rams-could-fall-apart-time-011500229.html"
    },
    {
      "kind": "rumor",
      "title": "2026 World Cup Odds: USMNT Generating Record-Breaking Soccer Handle",
      "title_ja": null,
      "excerpt": "The USA's Round of 32 match was historic from a gambling perspective, and the Round of 16 should be even bigger, Patrick Everson reports.",
      "excerpt_ja": null,
      "sources": [
        "FOX Sports NFL"
      ],
      "reliability": 0.5,
      "team_abbrev": null,
      "player_name": null,
      "coach_name": null,
      "published_at": "Thu, 02 Jul 2026 00:47:06 -0400",
      "url": "https://www.foxsports.com/stories/soccer/2026-world-cup-odds-usmnt-generating-record-breaking-soccer-handle"
    },
    {
      "kind": "other",
      "title": "Sports World Reacts To Folarin Balogun's Controversial Red Card In USA Win: 'Man What'",
      "title_ja": null,
      "excerpt": "Folarin Balogun received a controversial red card during the 64th minute of the matchup against Bosnia and Herzegovina.",
      "excerpt_ja": null,
      "sources": [
        "FOX Sports NFL"
      ],
      "reliability": 0.5,
      "team_abbrev": null,
      "player_name": null,
      "coach_name": null,
      "published_at": "Thu, 02 Jul 2026 00:44:27 -0400",
      "url": "https://www.foxsports.com/stories/soccer/sports-world-reacts-folarin-baloguns-controversial-red-card-usa-win-man-what"
    },
    {
      "kind": "signing",
      "title": "Athletics Slugger Brent Rooker Set for Season-Ending Left Knee Surgery",
      "title_ja": null,
      "excerpt": "Athletics designated hitter Brent Rooker will undergo surgery to repair a cartilage tear in his left knee and miss the remainder of the season.",
      "excerpt_ja": null,
      "sources": [
        "FOX Sports NFL"
      ],
      "reliability": 0.5,
      "team_abbrev": null,
      "player_name": null,
      "coach_name": null,
      "published_at": "Thu, 02 Jul 2026 00:41:10 -0400",
      "url": "https://www.foxsports.com/stories/mlb/athletics-slugger-brent-rooker-set-season-ending-left-knee-surgery"
    },
    {
      "kind": "other",
      "title": "Christian Pulisic Says Folarin Balogun 'Didn’t Deserve The Red Card' In World Cup Win",
      "title_ja": null,
      "excerpt": "Christian Pulisic praised the United States' team effort after they overcame a second-half red card to beat Bosnia and Herzegovina 2-0.",
      "excerpt_ja": null,
      "sources": [
        "FOX Sports NFL"
      ],
      "reliability": 0.5,
      "team_abbrev": null,
      "player_name": null,
      "coach_name": null,
      "published_at": "Thu, 02 Jul 2026 00:34:31 -0400",
      "url": "https://www.foxsports.com/stories/soccer/usa-bosnia-world-cup-pulisic-balogun-red-card"
    },
    {
      "kind": "other",
      "title": "Draft class 2024 check-in: 4 Rams no longer on team",
      "title_ja": null,
      "excerpt": "Rams drafted Jared Verse, Brennan Jackson, Josh Karty in 2024 and they’ll play elsewhere this season",
      "excerpt_ja": null,
      "sources": [
        "Yahoo Sports NFL"
      ],
      "reliability": 0.5,
      "team_abbrev": "LAR",
      "player_name": null,
      "coach_name": null,
      "published_at": "Thu, 02 Jul 2026 00:12:18 +0000",
      "url": "https://sports.yahoo.com/articles/draft-class-2024-check-4-001218936.html"
    },
    {
      "kind": "other",
      "title": "Will Cristiano Ronaldo Play Today? Portugal Star’s Status vs. Croatia",
      "title_ja": null,
      "excerpt": "Will Cristiano Ronaldo play today? Here's everything to know about his status ahead of Portugal vs. Croatia.",
      "excerpt_ja": null,
      "sources": [
        "FOX Sports NFL"
      ],
      "reliability": 0.5,
      "team_abbrev": null,
      "player_name": null,
      "coach_name": null,
      "published_at": "Thu, 02 Jul 2026 00:00:35 -0400",
      "url": "https://www.foxsports.com/stories/soccer/will-cristiano-ronaldo-play-today-portugal-stars-status-vs-croatia"
    },
    {
      "kind": "injury",
      "title": "Is Lamine Yamal Playing Today? Spain Star’s Status vs. Austria",
      "title_ja": null,
      "excerpt": "Will Lamine Yamal play against Austria? Here's everything to know about Yamal's status ahead of their round of 32 matchup.",
      "excerpt_ja": null,
      "sources": [
        "FOX Sports NFL"
      ],
      "reliability": 0.5,
      "team_abbrev": null,
      "player_name": null,
      "coach_name": null,
      "published_at": "Thu, 02 Jul 2026 00:00:28 -0400",
      "url": "https://www.foxsports.com/stories/soccer/lamine-yamal-playing-today-spain-stars-status-vs-austria"
    },
    {
      "kind": "other",
      "title": "Ranking NFL starting quarterbacks by tiers ahead of the 2026 season",
      "title_ja": null,
      "excerpt": "The NFL has never had more quarterback talent, but the gap between the league's elite, rising stars and stopgap starters remains as fascinating as ever",
      "excerpt_ja": null,
      "sources": [
        "CBS Sports NFL"
      ],
      "reliability": 0.5,
      "team_abbrev": null,
      "player_name": null,
      "coach_name": null,
      "published_at": "\n                        Wed, 01 Jul 2026 23:30:11 +0000\n                    ",
      "url": "https://www.cbssports.com/nfl/news/nfl-quarterback-rankings-2026-tiers/"
    },
    {
      "kind": "other",
      "title": "Former Titans scout Blaise Taylor found guilty of murdering his pregnant girlfriend",
      "title_ja": null,
      "excerpt": "Former NFL scout faces life in prison after being convicted in the poisoning deaths of his pregnant girlfriend and unborn child",
      "excerpt_ja": null,
      "sources": [
        "CBS Sports NFL"
      ],
      "reliability": 0.5,
      "team_abbrev": "TEN",
      "player_name": null,
      "coach_name": null,
      "published_at": "\n                        Wed, 01 Jul 2026 22:31:20 +0000\n                    ",
      "url": "https://www.cbssports.com/nfl/news/former-titans-scout-found-guilty-murdering-pregnant-girlfriend/"
    },
    {
      "kind": "rumor",
      "title": "Taylor Swift and Travis Kelce wedding rumors swirl: Everything we know about reported MSG ceremony",
      "title_ja": null,
      "excerpt": "Taylor Swift and Travis Kelce have not publicly confirmed wedding plans, but reports of road closures, private security and major setup work at Madison Square Garden have fans convinced something big is coming",
      "excerpt_ja": null,
      "sources": [
        "CBS Sports NFL"
      ],
      "reliability": 0.5,
      "team_abbrev": null,
      "player_name": null,
      "coach_name": null,
      "published_at": "\n                        Wed, 01 Jul 2026 20:16:03 +0000\n                    ",
      "url": "https://www.cbssports.com/nfl/news/taylor-swift-travis-kelce-wedding-rumors-madison-square-garden/"
    },
    {
      "kind": "other",
      "title": "Betting the Seahawks in 2026: See how Seattle's win total, Super Bowl odds are trending and our best bets",
      "title_ja": null,
      "excerpt": "We're breaking down Seahawks futures in our 2026 betting preview, featuring odds, trends, schedule and more",
      "excerpt_ja": null,
      "sources": [
        "CBS Sports NFL"
      ],
      "reliability": 0.5,
      "team_abbrev": "SEA",
      "player_name": null,
      "coach_name": null,
      "published_at": "\n                        Wed, 01 Jul 2026 18:50:28 +0000\n                    ",
      "url": "https://www.cbssports.com/nfl/news/betting-the-seahawks-in-2026-see-how-seattles-win-total-super-bowl-odds-are-trending-and-our-best-bets/"
    },
    {
      "kind": "other",
      "title": "Betting the 49ers in 2026: See how San Francisco's win total, Super Bowl odds are trending and our best bets",
      "title_ja": null,
      "excerpt": "We're breaking down 49ers futures in our 2026 betting preview, featuring odds, trends, schedule and more",
      "excerpt_ja": null,
      "sources": [
        "CBS Sports NFL"
      ],
      "reliability": 0.5,
      "team_abbrev": "SF",
      "player_name": null,
      "coach_name": null,
      "published_at": "\n                        Wed, 01 Jul 2026 18:48:32 +0000\n                    ",
      "url": "https://www.cbssports.com/nfl/news/betting-the-49ers-in-2026-see-how-san-franciscos-win-total-super-bowl-odds-are-trending-and-our-best-bets/"
    },
    {
      "kind": "other",
      "title": "Betting the Rams in 2026: See how Los Angeles' win total, Super Bowl odds are trending and our best bets",
      "title_ja": null,
      "excerpt": "We're breaking down Rams futures in our 2026 betting preview, featuring odds, trends, schedule and more",
      "excerpt_ja": null,
      "sources": [
        "CBS Sports NFL"
      ],
      "reliability": 0.5,
      "team_abbrev": "LAR",
      "player_name": null,
      "coach_name": null,
      "published_at": "\n                        Wed, 01 Jul 2026 18:46:49 +0000\n                    ",
      "url": "https://www.cbssports.com/nfl/news/betting-the-rams-in-2026-see-how-los-angeles-win-total-super-bowl-odds-are-trending-and-our-best-bets/"
    },
    {
      "kind": "other",
      "title": "Betting the Cardinals in 2026: See how Arizona's win total, Super Bowl odds are trending and our best bets",
      "title_ja": null,
      "excerpt": "We're breaking down Cardinals futures in our 2026 betting preview, featuring odds, trends, schedule and more",
      "excerpt_ja": null,
      "sources": [
        "CBS Sports NFL"
      ],
      "reliability": 0.5,
      "team_abbrev": "ARI",
      "player_name": null,
      "coach_name": null,
      "published_at": "\n                        Wed, 01 Jul 2026 18:45:08 +0000\n                    ",
      "url": "https://www.cbssports.com/nfl/news/betting-the-cardinals-in-2026-see-how-arizonas-win-total-super-bowl-odds-are-trending-and-our-best-bets/"
    },
    {
      "kind": "other",
      "title": "Betting the Buccaneers in 2026: See how Tampa Bay's win total, Super Bowl odds are trending and our best bets",
      "title_ja": null,
      "excerpt": "We're breaking down Buccaneers futures in our 2026 betting preview, featuring odds, trends, schedule and more",
      "excerpt_ja": null,
      "sources": [
        "CBS Sports NFL"
      ],
      "reliability": 0.5,
      "team_abbrev": "TB",
      "player_name": null,
      "coach_name": null,
      "published_at": "\n                        Wed, 01 Jul 2026 18:43:50 +0000\n                    ",
      "url": "https://www.cbssports.com/nfl/news/betting-the-buccaneers-in-2026-see-how-tampa-bays-win-total-super-bowl-odds-are-trending-and-our-best-bets/"
    },
    {
      "kind": "other",
      "title": "Betting the Saints in 2026: See how New Orleans' win total, Super Bowl odds are trending and our best bets",
      "title_ja": null,
      "excerpt": "We're breaking down Saints futures in our 2026 betting preview, featuring odds, trends, schedule and more",
      "excerpt_ja": null,
      "sources": [
        "CBS Sports NFL"
      ],
      "reliability": 0.5,
      "team_abbrev": "NO",
      "player_name": null,
      "coach_name": null,
      "published_at": "\n                        Wed, 01 Jul 2026 18:42:47 +0000\n                    ",
      "url": "https://www.cbssports.com/nfl/news/betting-the-saints-in-2026-see-how-new-orleans-win-total-super-bowl-odds-are-trending-and-our-best-bets/"
    },
    {
      "kind": "other",
      "title": "Betting the Panthers in 2026: See how Carolina's win total, Super Bowl odds are trending and our best bets",
      "title_ja": null,
      "excerpt": "We're breaking down Panthers futures in our 2026 betting preview, featuring odds, trends, schedule and more",
      "excerpt_ja": null,
      "sources": [
        "CBS Sports NFL"
      ],
      "reliability": 0.5,
      "team_abbrev": "CAR",
      "player_name": null,
      "coach_name": null,
      "published_at": "\n                        Wed, 01 Jul 2026 18:40:30 +0000\n                    ",
      "url": "https://www.cbssports.com/nfl/news/betting-the-panthers-in-2026-see-how-carolinas-win-total-super-bowl-odds-are-trending-and-our-best-bets/"
    },
    {
      "kind": "other",
      "title": "Betting the Falcons in 2026: See how Atlanta's win total, Super Bowl odds are trending and our best bets",
      "title_ja": null,
      "excerpt": "We're breaking down Falcons futures in our 2026 betting preview, featuring odds, trends, schedule and more",
      "excerpt_ja": null,
      "sources": [
        "CBS Sports NFL"
      ],
      "reliability": 0.5,
      "team_abbrev": "ATL",
      "player_name": null,
      "coach_name": null,
      "published_at": "\n                        Wed, 01 Jul 2026 18:38:59 +0000\n                    ",
      "url": "https://www.cbssports.com/nfl/news/betting-the-falcons-in-2026-see-how-atlantas-win-total-super-bowl-odds-are-trending-and-our-best-bets/"
    },
    {
      "kind": "other",
      "title": "Betting the Chiefs in 2026: See how Kansas City's win total, Super Bowl odds are trending and our best bets",
      "title_ja": null,
      "excerpt": "We're breaking down Chiefs futures in our 2026 betting preview, featuring odds, trends, schedule and more",
      "excerpt_ja": null,
      "sources": [
        "CBS Sports NFL"
      ],
      "reliability": 0.5,
      "team_abbrev": "KC",
      "player_name": null,
      "coach_name": null,
      "published_at": "\n                        Wed, 01 Jul 2026 18:37:39 +0000\n                    ",
      "url": "https://www.cbssports.com/nfl/news/betting-the-chiefs-in-2026-see-how-kansas-citys-win-total-super-bowl-odds-are-trending-and-our-best-bets/"
    },
    {
      "kind": "other",
      "title": "Betting the Vikings in 2026: See how Minnesota's win total, Super Bowl odds are trending and our best bets",
      "title_ja": null,
      "excerpt": "We're breaking down Vikings futures in our 2026 betting preview, featuring odds, trends, schedule and more",
      "excerpt_ja": null,
      "sources": [
        "CBS Sports NFL"
      ],
      "reliability": 0.5,
      "team_abbrev": "MIN",
      "player_name": null,
      "coach_name": null,
      "published_at": "\n                        Wed, 01 Jul 2026 18:33:36 +0000\n                    ",
      "url": "https://www.cbssports.com/nfl/news/betting-the-vikings-in-2026-see-how-minnesotas-win-total-super-bowl-odds-are-trending-and-our-best-bets/"
    },
    {
      "kind": "injury",
      "title": "Agent's Take: How Rams can protect themselves when making a huge financial commitment to Puka Nacua",
      "title_ja": null,
      "excerpt": "The Rams could look to a Chiefs blueprint with Tyreek Hill to secure their star wideout while protecting themselves against off-field concerns",
      "excerpt_ja": null,
      "sources": [
        "CBS Sports NFL"
      ],
      "reliability": 0.5,
      "team_abbrev": "KC",
      "player_name": null,
      "coach_name": null,
      "published_at": "\n                        Wed, 01 Jul 2026 18:32:53 +0000\n                    ",
      "url": "https://www.cbssports.com/nfl/news/rams-puka-nacua-new-contract-protection-wide-receiver-nfl/"
    },
    {
      "kind": "other",
      "title": "Betting the Packers in 2026: See how Green Bay's win total, Super Bowl odds are trending and our best bets",
      "title_ja": null,
      "excerpt": "We're breaking down Packers futures in our 2026 betting preview, featuring odds, trends, schedule and more",
      "excerpt_ja": null,
      "sources": [
        "CBS Sports NFL"
      ],
      "reliability": 0.5,
      "team_abbrev": "GB",
      "player_name": null,
      "coach_name": null,
      "published_at": "\n                        Wed, 01 Jul 2026 18:31:13 +0000\n                    ",
      "url": "https://www.cbssports.com/nfl/news/betting-the-packers-in-2026-see-how-green-bays-win-total-super-bowl-odds-are-trending-and-our-best-bets/"
    },
    {
      "kind": "other",
      "title": "Betting the Lions in 2026: See how Detroit's win total, Super Bowl odds are trending and our best bets",
      "title_ja": null,
      "excerpt": "We're breaking down Lions futures in our 2026 betting preview, featuring odds, trends, schedule and more",
      "excerpt_ja": null,
      "sources": [
        "CBS Sports NFL"
      ],
      "reliability": 0.5,
      "team_abbrev": "DET",
      "player_name": null,
      "coach_name": null,
      "published_at": "\n                        Wed, 01 Jul 2026 18:29:05 +0000\n                    ",
      "url": "https://www.cbssports.com/nfl/news/betting-the-lions-in-2026-see-how-detroits-win-total-super-bowl-odds-are-trending-and-our-best-bets/"
    },
    {
      "kind": "other",
      "title": "Betting the Bears in 2026: See how Chicago's win total, Super Bowl odds are trending and our best bets",
      "title_ja": null,
      "excerpt": "We're breaking down Bears futures in our 2026 betting preview, featuring odds, trends, schedule and more",
      "excerpt_ja": null,
      "sources": [
        "CBS Sports NFL"
      ],
      "reliability": 0.5,
      "team_abbrev": "CHI",
      "player_name": null,
      "coach_name": null,
      "published_at": "\n                        Wed, 01 Jul 2026 18:22:47 +0000\n                    ",
      "url": "https://www.cbssports.com/nfl/news/betting-the-bears-in-2026-see-how-chicagos-win-total-super-bowl-odds-are-trending-and-our-best-bets/"
    },
    {
      "kind": "other",
      "title": "Betting the Commanders in 2026: See how Washington's win total, Super Bowl odds are trending and our best bets",
      "title_ja": null,
      "excerpt": "We're breaking down Commanders futures in our 2026 betting preview, featuring odds, trends, schedule and more",
      "excerpt_ja": null,
      "sources": [
        "CBS Sports NFL"
      ],
      "reliability": 0.5,
      "team_abbrev": "WAS",
      "player_name": null,
      "coach_name": null,
      "published_at": "\n                        Wed, 01 Jul 2026 18:20:51 +0000\n                    ",
      "url": "https://www.cbssports.com/nfl/news/betting-the-commanders-in-2026-see-how-washingtons-win-total-super-bowl-odds-are-trending-and-our-best-bets/"
    },
    {
      "kind": "other",
      "title": "Betting the Eagles in 2026: See how Philadelphia's win total, Super Bowl odds are trending and our best bets",
      "title_ja": null,
      "excerpt": "We're breaking down Eagles futures in our 2026 betting preview, featuring odds, trends, schedule and more",
      "excerpt_ja": null,
      "sources": [
        "CBS Sports NFL"
      ],
      "reliability": 0.5,
      "team_abbrev": "PHI",
      "player_name": null,
      "coach_name": null,
      "published_at": "\n                        Wed, 01 Jul 2026 18:17:56 +0000\n                    ",
      "url": "https://www.cbssports.com/nfl/news/betting-the-eagles-in-2026-see-how-philadelphias-win-total-super-bowl-odds-are-trending-and-our-best-bets/"
    },
    {
      "kind": "other",
      "title": "Betting the Giants in 2026: See how New York's win total, Super Bowl odds are trending and our best bets",
      "title_ja": null,
      "excerpt": "We're breaking down Giants futures in our 2026 betting preview, featuring odds, trends, schedule and more",
      "excerpt_ja": null,
      "sources": [
        "CBS Sports NFL"
      ],
      "reliability": 0.5,
      "team_abbrev": "NYG",
      "player_name": null,
      "coach_name": null,
      "published_at": "\n                        Wed, 01 Jul 2026 18:13:57 +0000\n                    ",
      "url": "https://www.cbssports.com/nfl/news/betting-the-giants-in-2026-see-how-new-yorks-win-total-super-bowl-odds-are-trending-and-our-best-bets/"
    },
    {
      "kind": "other",
      "title": "Betting the Cowboys in 2026: See how Dallas' win total, Super Bowl odds are trending and our best bets",
      "title_ja": null,
      "excerpt": "We're breaking down Cowboys futures in our 2026 betting preview, featuring odds, trends, schedule and more",
      "excerpt_ja": null,
      "sources": [
        "CBS Sports NFL"
      ],
      "reliability": 0.5,
      "team_abbrev": "DAL",
      "player_name": null,
      "coach_name": null,
      "published_at": "\n                        Wed, 01 Jul 2026 18:10:28 +0000\n                    ",
      "url": "https://www.cbssports.com/nfl/news/betting-the-cowboys-in-2026-see-how-dallas-win-total-super-bowl-odds-are-trending-and-our-best-bets/"
    },
    {
      "kind": "other",
      "title": "Betting the Chargers in 2026: See how Los Angeles' win total, Super Bowl odds are trending and our best bets",
      "title_ja": null,
      "excerpt": "We're breaking down Chargers futures in our 2026 betting preview, featuring odds, trends, schedule and more",
      "excerpt_ja": null,
      "sources": [
        "CBS Sports NFL"
      ],
      "reliability": 0.5,
      "team_abbrev": "LAC",
      "player_name": null,
      "coach_name": null,
      "published_at": "\n                        Wed, 01 Jul 2026 15:51:50 +0000\n                    ",
      "url": "https://www.cbssports.com/nfl/news/betting-the-chargers-in-2026-see-how-los-angeles-win-total-super-bowl-odds-are-trending-and-our-best-bets/"
    },
    {
      "kind": "other",
      "title": "Betting the Raiders in 2026: See how Las Vegas' win total, Super Bowl odds are trending and our best bets",
      "title_ja": null,
      "excerpt": "We're breaking down Raiders futures in our 2026 betting preview, featuring odds, trends, schedule and more",
      "excerpt_ja": null,
      "sources": [
        "CBS Sports NFL"
      ],
      "reliability": 0.5,
      "team_abbrev": "LV",
      "player_name": null,
      "coach_name": null,
      "published_at": "\n                        Wed, 01 Jul 2026 15:50:51 +0000\n                    ",
      "url": "https://www.cbssports.com/nfl/news/betting-the-raiders-in-2026-see-how-las-vegas-win-total-super-bowl-odds-are-trending-and-our-best-bets/"
    },
    {
      "kind": "other",
      "title": "Betting the Broncos in 2026: See how Denver's win total, Super Bowl odds are trending and our best bets",
      "title_ja": null,
      "excerpt": "We're breaking down Broncos futures in our 2026 betting preview, featuring odds, trends, schedule and more",
      "excerpt_ja": null,
      "sources": [
        "CBS Sports NFL"
      ],
      "reliability": 0.5,
      "team_abbrev": "DEN",
      "player_name": null,
      "coach_name": null,
      "published_at": "\n                        Wed, 01 Jul 2026 15:47:13 +0000\n                    ",
      "url": "https://www.cbssports.com/nfl/news/betting-the-broncos-in-2026-see-how-denvers-win-total-super-bowl-odds-are-trending-and-our-best-bets/"
    },
    {
      "kind": "other",
      "title": "Betting the Titans in 2026: See how Tennessee's win total, Super Bowl odds are trending and our best bets",
      "title_ja": null,
      "excerpt": "We're breaking down Titans futures in our 2026 betting preview, featuring odds, trends, schedule and more",
      "excerpt_ja": null,
      "sources": [
        "CBS Sports NFL"
      ],
      "reliability": 0.5,
      "team_abbrev": "TEN",
      "player_name": null,
      "coach_name": null,
      "published_at": "\n                        Wed, 01 Jul 2026 15:44:36 +0000\n                    ",
      "url": "https://www.cbssports.com/nfl/news/betting-the-titans-in-2026-see-how-tennessees-win-total-super-bowl-odds-are-trending-and-our-best-bets/"
    },
    {
      "kind": "other",
      "title": "Betting the Jaguars in 2026: See how Jacksonville's win total, Super Bowl odds are trending and our best bets",
      "title_ja": null,
      "excerpt": "We're breaking down Jaguars futures in our 2026 betting preview, featuring odds, trends, schedule and more",
      "excerpt_ja": null,
      "sources": [
        "CBS Sports NFL"
      ],
      "reliability": 0.5,
      "team_abbrev": "JAX",
      "player_name": null,
      "coach_name": null,
      "published_at": "\n                        Wed, 01 Jul 2026 15:42:32 +0000\n                    ",
      "url": "https://www.cbssports.com/nfl/news/betting-the-jaguars-in-2026-see-how-jacksonvilles-win-total-super-bowl-odds-are-trending-and-our-best-bets/"
    },
    {
      "kind": "other",
      "title": "Betting the Colts in 2026: See how Indianapolis' win total, Super Bowl odds are trending and our best bets",
      "title_ja": null,
      "excerpt": "We're breaking down Colts futures in our 2026 betting preview, featuring odds, trends, schedule and more",
      "excerpt_ja": null,
      "sources": [
        "CBS Sports NFL"
      ],
      "reliability": 0.5,
      "team_abbrev": "IND",
      "player_name": null,
      "coach_name": null,
      "published_at": "\n                        Wed, 01 Jul 2026 15:41:33 +0000\n                    ",
      "url": "https://www.cbssports.com/nfl/news/betting-the-colts-in-2026-see-how-indianapolis-win-total-super-bowl-odds-are-trending-and-our-best-bets/"
    },
    {
      "kind": "other",
      "title": "Betting the Texans in 2026: See how Houston's win total, Super Bowl odds are trending and our best bets",
      "title_ja": null,
      "excerpt": "We're breaking down Texans futures in our 2026 betting preview, featuring odds, trends, schedule and more",
      "excerpt_ja": null,
      "sources": [
        "CBS Sports NFL"
      ],
      "reliability": 0.5,
      "team_abbrev": "HOU",
      "player_name": null,
      "coach_name": null,
      "published_at": "\n                        Wed, 01 Jul 2026 15:40:06 +0000\n                    ",
      "url": "https://www.cbssports.com/nfl/news/betting-the-texans-in-2026-see-how-houstons-win-total-super-bowl-odds-are-trending-and-our-best-bets/"
    },
    {
      "kind": "other",
      "title": "Betting the Steelers in 2026: See how Pittsburgh's win total, Super Bowl odds are trending and our best bets",
      "title_ja": null,
      "excerpt": "We're breaking down Steelers futures in our 2026 betting preview, featuring odds, trends, schedule and more",
      "excerpt_ja": null,
      "sources": [
        "CBS Sports NFL"
      ],
      "reliability": 0.5,
      "team_abbrev": "PIT",
      "player_name": null,
      "coach_name": null,
      "published_at": "\n                        Wed, 01 Jul 2026 15:36:54 +0000\n                    ",
      "url": "https://www.cbssports.com/nfl/news/betting-the-steelers-in-2026-see-how-pittsburghs-win-total-super-bowl-odds-are-trending-and-our-best-bets/"
    },
    {
      "kind": "trade",
      "title": "NFL trade rumors: Eight players who could change teams before 2026 season kicks off",
      "title_ja": null,
      "excerpt": "Brandon Aiyuk, Anthony Richardson Sr., Maxx Crosby and Alvin Kamara headline a group of players whose futures could come into focus before the 2026 NFL season begins",
      "excerpt_ja": null,
      "sources": [
        "CBS Sports NFL"
      ],
      "reliability": 0.5,
      "team_abbrev": null,
      "player_name": null,
      "coach_name": null,
      "published_at": "\n                        Thu, 02 Jul 2026 12:51:04 +0000\n                    ",
      "url": "https://www.cbssports.com/nfl/news/nfl-trade-rumors-brandon-aiyuk-maxx-crosby-week-1/"
    }
  ]
}